axonode/__init__.py
axonode/core.py
axonode-0.0.0a0.dist-info/licenses/LICENSE
axonode-0.0.0a0.dist-info/.gitignore
axonode-0.0.0a0.dist-info/METADATA
axonode-0.0.0a0.dist-info/WHEEL
axonode-0.0.0a0.dist-info/top_level.txt
axonode-0.0.0a0.dist-info/RECORD
