Metadata-Version: 2.4
Name: axonode
Version: 0.0.0a0
Summary: Work-in-progress graph-memory engine
Author-email: Erez Azaria <bazilicum@users.noreply.github.com>
License-Expression: MIT
Classifier: Development Status :: 1 - Planning
Requires-Python: >=3.9
License-File: LICENSE
Dynamic: license-file
